herostatus/__init__.py
herostatus/herostatus.py
herostatus/logo.uni
herostatus/sounds/burglaralarm.wav
herostatus/sounds/caralarm.wav
herostatus/sounds/hiphopalarm.wav
herostatus/sounds/nuclearalarm.wav
herostatus/sounds/sirenalarm.wav
herostatus/sounds/strongbadalarm.wav
Herostatus-0.3.5.dist-info/METADATA
Herostatus-0.3.5.dist-info/WHEEL
Herostatus-0.3.5.dist-info/entry_points.txt
Herostatus-0.3.5.dist-info/top_level.txt
Herostatus-0.3.5.dist-info/RECORD
