Metadata-Version: 2.1
Name: Herostatus
Version: 0.3.5
Summary: Herominers console status and stats display for cryptonight miners
Home-page: https://github.com/freqnik/herostatus
Author: freQniK
Author-email: freqnik@mathnodes.com
License: GPLv3
Keywords: crypto cryptonight zephyr bitcoin monero haven dero ergo blockchain mining randomx
Classifier: Programming Language :: Python
Classifier: Programming Language :: Python :: 3
Requires-Dist: requests
Requires-Dist: pygame
